odoo/addons/purchase_order_price_recalculation/README.rst
odoo/addons/purchase_order_price_recalculation/__init__.py
odoo/addons/purchase_order_price_recalculation/__manifest__.py
odoo/addons/purchase_order_price_recalculation/i18n/es.po
odoo/addons/purchase_order_price_recalculation/i18n/it.po
odoo/addons/purchase_order_price_recalculation/i18n/purchase_order_price_recalculation.pot
odoo/addons/purchase_order_price_recalculation/models/__init__.py
odoo/addons/purchase_order_price_recalculation/models/purchase_order.py
odoo/addons/purchase_order_price_recalculation/readme/CONTRIBUTORS.rst
odoo/addons/purchase_order_price_recalculation/readme/DESCRIPTION.rst
odoo/addons/purchase_order_price_recalculation/readme/USAGE.rst
odoo/addons/purchase_order_price_recalculation/static/description/icon.png
odoo/addons/purchase_order_price_recalculation/static/description/index.html
odoo/addons/purchase_order_price_recalculation/tests/__init__.py
odoo/addons/purchase_order_price_recalculation/tests/test_purchase_order_price_recalculation.py
odoo/addons/purchase_order_price_recalculation/views/purchase_order_view.xml
odoo14_addon_purchase_order_price_recalculation-14.0.1.0.1.dev6.dist-info/METADATA
odoo14_addon_purchase_order_price_recalculation-14.0.1.0.1.dev6.dist-info/WHEEL
odoo14_addon_purchase_order_price_recalculation-14.0.1.0.1.dev6.dist-info/top_level.txt
odoo14_addon_purchase_order_price_recalculation-14.0.1.0.1.dev6.dist-info/RECORD
